{
  "id": "m416dcfa2",
  "name": "Lビッグドリーム THE GOLDEN PUSHER",
  "manufacturer": "サミー",
  "aliases": [
    "Lビッグドリーム THE GOLDEN PUSHER",
    "ゴールデンプッシャー"
  ],
  "thumb": null,
  "available": true,
  "releaseDate": "2026-05-11",
  "lastUpdated": "2026-07-08",
  "meta": {
    "samples": "91",
    "source": "実戦データ自動収集（2026-06-09〜2026-07-06・全データ）／機械割=回収円÷投資円（46/52は460枚投資=520枚回収、50/50は500枚投資=500枚回収で100%・タブでレート切替）／閉店時ハマり（打ち切り6台日）を損失計上済み／設定状況は収集日に依存"
  },
  "atPayout": {
    "step": 50,
    "label": "AT初当たり時 平均獲得（当選G帯別）",
    "note": "1AT＝初当たり〜引き戻し終了の総獲得。当選G（AT・RB間ハマりG）を 0-70 / 71-99 / 以降100Gから50G帯 で集計。",
    "bands": [
      {
        "lo": 0,
        "hi": 71,
        "count": 1,
        "mean": 0.0,
        "median": 0
      },
      {
        "lo": 71,
        "hi": 100,
        "count": 4,
        "mean": 79.2,
        "median": 0
      },
      {
        "lo": 100,
        "hi": 150,
        "count": 9,
        "mean": 717.2,
        "median": 305
      },
      {
        "lo": 150,
        "hi": 200,
        "count": 12,
        "mean": 860.3,
        "median": 149
      },
      {
        "lo": 200,
        "hi": 250,
        "count": 8,
        "mean": 682.2,
        "median": 407
      },
      {
        "lo": 250,
        "hi": 300,
        "count": 11,
        "mean": 205.5,
        "median": 0
      },
      {
        "lo": 300,
        "hi": 350,
        "count": 6,
        "mean": 1740.3,
        "median": 742
      },
      {
        "lo": 350,
        "hi": 400,
        "count": 7,
        "mean": 1202.6,
        "median": 413
      },
      {
        "lo": 400,
        "hi": 450,
        "count": 5,
        "mean": 223.4,
        "median": 0
      },
      {
        "lo": 450,
        "hi": 500,
        "count": 2,
        "mean": 406.5,
        "median": 406
      },
      {
        "lo": 500,
        "hi": 550,
        "count": 5,
        "mean": 367.0,
        "median": 321
      },
      {
        "lo": 550,
        "hi": 600,
        "count": 6,
        "mean": 909.7,
        "median": 312
      },
      {
        "lo": 600,
        "hi": 650,
        "count": 8,
        "mean": 739.1,
        "median": 402
      },
      {
        "lo": 650,
        "hi": 700,
        "count": 1,
        "mean": 1185.0,
        "median": 1185
      },
      {
        "lo": 700,
        "hi": 750,
        "count": 3,
        "mean": 139.3,
        "median": 0
      },
      {
        "lo": 900,
        "hi": 950,
        "count": 1,
        "mean": 0.0,
        "median": 0
      },
      {
        "lo": 950,
        "hi": 1000,
        "count": 1,
        "mean": 997.0,
        "median": 997
      },
      {
        "lo": 1500,
        "hi": 1550,
        "count": 1,
        "mean": 812.0,
        "median": 812
      }
    ]
  },
  "evCalc": {
    "use": 1.61,
    "junzou": 8.2,
    "ceiling": 1499,
    "step": 10
  },
  "profiles": [
    {
      "key": "game_ceiling_4652",
      "label": "ゲーム数天井・46/52",
      "ceiling": "1499G",
      "gRange": {
        "start": 0,
        "end": 610,
        "step": 10
      },
      "activeAxes": [
        "rate"
      ],
      "baseAnchors": [
        {
          "g": 0,
          "ev": 38,
          "rtp": 100.3,
          "n": 97,
          "inv": 566,
          "playG": 430
        },
        {
          "g": 10,
          "ev": 393,
          "rtp": 103.2,
          "n": 95,
          "inv": 561,
          "playG": 429
        },
        {
          "g": 20,
          "ev": 743,
          "rtp": 106.3,
          "n": 95,
          "inv": 545,
          "playG": 419
        },
        {
          "g": 30,
          "ev": 1093,
          "rtp": 109.5,
          "n": 95,
          "inv": 529,
          "playG": 409
        },
        {
          "g": 40,
          "ev": 1443,
          "rtp": 112.9,
          "n": 95,
          "inv": 513,
          "playG": 399
        },
        {
          "g": 50,
          "ev": 1809,
          "rtp": 116.6,
          "n": 94,
          "inv": 502,
          "playG": 393
        },
        {
          "g": 60,
          "ev": 2159,
          "rtp": 120.4,
          "n": 94,
          "inv": 486,
          "playG": 383
        },
        {
          "g": 70,
          "ev": 2509,
          "rtp": 124.5,
          "n": 94,
          "inv": 470,
          "playG": 373
        },
        {
          "g": 80,
          "ev": 2859,
          "rtp": 129.0,
          "n": 94,
          "inv": 454,
          "playG": 363
        },
        {
          "g": 90,
          "ev": 3243,
          "rtp": 133.0,
          "n": 91,
          "inv": 453,
          "playG": 364
        },
        {
          "g": 100,
          "ev": 3667,
          "rtp": 137.8,
          "n": 89,
          "inv": 447,
          "playG": 362
        },
        {
          "g": 110,
          "ev": 4082,
          "rtp": 142.1,
          "n": 86,
          "inv": 446,
          "playG": 364
        },
        {
          "g": 120,
          "ev": 3421,
          "rtp": 135.3,
          "n": 83,
          "inv": 445,
          "playG": 360
        },
        {
          "g": 130,
          "ev": 3815,
          "rtp": 140.4,
          "n": 82,
          "inv": 435,
          "playG": 354
        },
        {
          "g": 140,
          "ev": 4216,
          "rtp": 145.8,
          "n": 81,
          "inv": 424,
          "playG": 348
        },
        {
          "g": 150,
          "ev": 4460,
          "rtp": 148.4,
          "n": 78,
          "inv": 424,
          "playG": 350
        },
        {
          "g": 160,
          "ev": 4876,
          "rtp": 152.2,
          "n": 74,
          "inv": 430,
          "playG": 357
        },
        {
          "g": 170,
          "ev": 5226,
          "rtp": 158.1,
          "n": 74,
          "inv": 414,
          "playG": 347
        },
        {
          "g": 180,
          "ev": 5796,
          "rtp": 162.4,
          "n": 69,
          "inv": 427,
          "playG": 361
        },
        {
          "g": 190,
          "ev": 4758,
          "rtp": 151.6,
          "n": 67,
          "inv": 424,
          "playG": 352
        },
        {
          "g": 200,
          "ev": 4149,
          "rtp": 146.1,
          "n": 66,
          "inv": 414,
          "playG": 341
        },
        {
          "g": 210,
          "ev": 4563,
          "rtp": 151.9,
          "n": 65,
          "inv": 404,
          "playG": 336
        },
        {
          "g": 220,
          "ev": 4863,
          "rtp": 156.7,
          "n": 64,
          "inv": 394,
          "playG": 330
        },
        {
          "g": 230,
          "ev": 5095,
          "rtp": 160.0,
          "n": 62,
          "inv": 391,
          "playG": 329
        },
        {
          "g": 240,
          "ev": 5401,
          "rtp": 164.2,
          "n": 60,
          "inv": 387,
          "playG": 328
        },
        {
          "g": 250,
          "ev": 4795,
          "rtp": 157.4,
          "n": 58,
          "inv": 384,
          "playG": 322
        },
        {
          "g": 260,
          "ev": 5212,
          "rtp": 162.8,
          "n": 56,
          "inv": 382,
          "playG": 323
        },
        {
          "g": 270,
          "ev": 5446,
          "rtp": 164.7,
          "n": 53,
          "inv": 387,
          "playG": 328
        },
        {
          "g": 280,
          "ev": 5831,
          "rtp": 168.1,
          "n": 50,
          "inv": 394,
          "playG": 336
        },
        {
          "g": 290,
          "ev": 6435,
          "rtp": 175.2,
          "n": 48,
          "inv": 393,
          "playG": 339
        },
        {
          "g": 300,
          "ev": 6924,
          "rtp": 182.6,
          "n": 47,
          "inv": 386,
          "playG": 337
        },
        {
          "g": 310,
          "ev": 7152,
          "rtp": 187.1,
          "n": 46,
          "inv": 378,
          "playG": 332
        },
        {
          "g": 320,
          "ev": 5724,
          "rtp": 171.2,
          "n": 45,
          "inv": 370,
          "playG": 317
        },
        {
          "g": 330,
          "ev": 5885,
          "rtp": 174.8,
          "n": 44,
          "inv": 362,
          "playG": 312
        },
        {
          "g": 340,
          "ev": 4658,
          "rtp": 159.1,
          "n": 42,
          "inv": 363,
          "playG": 305
        },
        {
          "g": 350,
          "ev": 4926,
          "rtp": 163.8,
          "n": 41,
          "inv": 355,
          "playG": 301
        },
        {
          "g": 360,
          "ev": 4737,
          "rtp": 157.9,
          "n": 37,
          "inv": 376,
          "playG": 316
        },
        {
          "g": 370,
          "ev": 5224,
          "rtp": 164.9,
          "n": 36,
          "inv": 370,
          "playG": 314
        },
        {
          "g": 380,
          "ev": 5373,
          "rtp": 167.7,
          "n": 35,
          "inv": 365,
          "playG": 311
        },
        {
          "g": 390,
          "ev": 2912,
          "rtp": 137.3,
          "n": 34,
          "inv": 359,
          "playG": 291
        },
        {
          "g": 400,
          "ev": 3112,
          "rtp": 140.4,
          "n": 33,
          "inv": 354,
          "playG": 288
        },
        {
          "g": 410,
          "ev": 3568,
          "rtp": 147.1,
          "n": 32,
          "inv": 349,
          "playG": 287
        },
        {
          "g": 420,
          "ev": 3654,
          "rtp": 147.4,
          "n": 30,
          "inv": 355,
          "playG": 293
        },
        {
          "g": 430,
          "ev": 4004,
          "rtp": 154.4,
          "n": 30,
          "inv": 339,
          "playG": 283
        },
        {
          "g": 440,
          "ev": 4443,
          "rtp": 159.0,
          "n": 28,
          "inv": 346,
          "playG": 291
        },
        {
          "g": 450,
          "ev": 4793,
          "rtp": 166.8,
          "n": 28,
          "inv": 330,
          "playG": 281
        },
        {
          "g": 460,
          "ev": 4971,
          "rtp": 170.2,
          "n": 27,
          "inv": 326,
          "playG": 279
        },
        {
          "g": 470,
          "ev": 5290,
          "rtp": 175.6,
          "n": 26,
          "inv": 322,
          "playG": 278
        },
        {
          "g": 480,
          "ev": 5640,
          "rtp": 184.8,
          "n": 26,
          "inv": 306,
          "playG": 268
        },
        {
          "g": 490,
          "ev": 5990,
          "rtp": 195.1,
          "n": 26,
          "inv": 290,
          "playG": 258
        },
        {
          "g": 500,
          "ev": 6340,
          "rtp": 206.5,
          "n": 26,
          "inv": 274,
          "playG": 248
        },
        {
          "g": 510,
          "ev": 6952,
          "rtp": 219.2,
          "n": 25,
          "inv": 268,
          "playG": 248
        },
        {
          "g": 520,
          "ev": 6764,
          "rtp": 218.3,
          "n": 24,
          "inv": 263,
          "playG": 243
        },
        {
          "g": 530,
          "ev": 7114,
          "rtp": 232.5,
          "n": 24,
          "inv": 247,
          "playG": 233
        },
        {
          "g": 540,
          "ev": 7764,
          "rtp": 234.5,
          "n": 21,
          "inv": 266,
          "playG": 251
        },
        {
          "g": 550,
          "ev": 8114,
          "rtp": 249.6,
          "n": 21,
          "inv": 249,
          "playG": 241
        },
        {
          "g": 560,
          "ev": 8203,
          "rtp": 245.9,
          "n": 19,
          "inv": 259,
          "playG": 248
        },
        {
          "g": 570,
          "ev": 8684,
          "rtp": 255.8,
          "n": 18,
          "inv": 256,
          "playG": 250
        },
        {
          "g": 580,
          "ev": 9772,
          "rtp": 265.7,
          "n": 16,
          "inv": 271,
          "playG": 268
        },
        {
          "g": 590,
          "ev": 10122,
          "rtp": 282.5,
          "n": 16,
          "inv": 255,
          "playG": 258
        },
        {
          "g": 600,
          "ev": 6395,
          "rtp": 215.0,
          "n": 15,
          "inv": 256,
          "playG": 235
        },
        {
          "g": 610,
          "ev": 6745,
          "rtp": 229.5,
          "n": 15,
          "inv": 240,
          "playG": 225
        }
      ],
      "zones": [],
      "totalPayout": 62222,
      "firstHitRate": 367,
      "ev": {
        "tai": 21.7391,
        "kan": 19.2308,
        "minSess": 15,
        "hits": [
          [
            "673",
            "2026-06-17",
            724,
            0
          ],
          [
            "673",
            "2026-06-17",
            221,
            494
          ],
          [
            "673",
            "2026-06-17",
            187,
            5041
          ],
          [
            "673",
            "2026-06-17",
            224,
            403
          ],
          [
            "673",
            "2026-06-17",
            125,
            0
          ],
          [
            "673",
            "2026-06-17",
            531,
            476
          ],
          [
            "673",
            "2026-06-17",
            321,
            733
          ],
          [
            "673",
            "2026-06-17",
            239,
            0
          ],
          [
            "673",
            "2026-06-17",
            531,
            0
          ],
          [
            "673",
            "2026-06-17",
            91,
            0
          ],
          [
            "673",
            "2026-06-17",
            157,
            713
          ],
          [
            "673",
            "2026-06-17",
            616,
            396
          ],
          [
            "673",
            "2026-06-17",
            994,
            997
          ],
          [
            "673",
            "2026-06-17",
            176,
            0
          ],
          [
            "673",
            "2026-06-17",
            572,
            307
          ],
          [
            "673",
            "2026-06-17",
            513,
            1038
          ],
          [
            "675",
            "2026-06-17",
            558,
            1122
          ],
          [
            "675",
            "2026-06-17",
            286,
            0
          ],
          [
            "675",
            "2026-06-17",
            746,
            0
          ],
          [
            "675",
            "2026-06-17",
            464,
            308
          ],
          [
            "675",
            "2026-06-17",
            385,
            5257
          ],
          [
            "675",
            "2026-06-17",
            408,
            0
          ],
          [
            "675",
            "2026-06-17",
            143,
            302
          ],
          [
            "675",
            "2026-06-17",
            613,
            3673
          ],
          [
            "675",
            "2026-06-17",
            119,
            641
          ],
          [
            "675",
            "2026-06-17",
            273,
            392
          ],
          [
            "675",
            "2026-06-17",
            370,
            638
          ],
          [
            "675",
            "2026-06-17",
            1501,
            812
          ],
          [
            "677",
            "2026-06-17",
            357,
            0
          ],
          [
            "677",
            "2026-06-17",
            179,
            0
          ],
          [
            "677",
            "2026-06-17",
            239,
            698
          ],
          [
            "677",
            "2026-06-17",
            344,
            424
          ],
          [
            "677",
            "2026-06-17",
            180,
            411
          ],
          [
            "677",
            "2026-06-17",
            578,
            0
          ],
          [
            "677",
            "2026-06-17",
            338,
            3330
          ],
          [
            "677",
            "2026-06-17",
            353,
            1332
          ],
          [
            "677",
            "2026-06-17",
            107,
            305
          ],
          [
            "677",
            "2026-06-17",
            553,
            0
          ],
          [
            "677",
            "2026-06-17",
            118,
            4404
          ],
          [
            "677",
            "2026-06-17",
            458,
            505
          ],
          [
            "677",
            "2026-06-17",
            293,
            0
          ],
          [
            "677",
            "2026-06-17",
            156,
            0
          ],
          [
            "677",
            "2026-06-17",
            195,
            3546
          ],
          [
            "677",
            "2026-06-17",
            254,
            315
          ],
          [
            "677",
            "2026-06-17",
            200,
            0
          ],
          [
            "677",
            "2026-06-17",
            153,
            0
          ],
          [
            "677",
            "2026-06-17",
            644,
            811
          ],
          [
            "679",
            "2026-06-17",
            175,
            298
          ],
          [
            "679",
            "2026-06-17",
            536,
            321
          ],
          [
            "679",
            "2026-06-17",
            85,
            0
          ],
          [
            "679",
            "2026-06-17",
            634,
            0
          ],
          [
            "679",
            "2026-06-17",
            696,
            1185
          ],
          [
            "679",
            "2026-06-17",
            335,
            750
          ],
          [
            "679",
            "2026-06-17",
            274,
            394
          ],
          [
            "679",
            "2026-06-17",
            567,
            317
          ],
          [
            "679",
            "2026-06-17",
            264,
            0
          ],
          [
            "679",
            "2026-06-17",
            266,
            838
          ],
          [
            "679",
            "2026-06-17",
            640,
            408
          ],
          [
            "679",
            "2026-06-17",
            157,
            0
          ],
          [
            "679",
            "2026-06-17",
            415,
            0
          ],
          [
            "679",
            "2026-06-17",
            140,
            497
          ],
          [
            "679",
            "2026-06-17",
            506,
            0
          ],
          [
            "679",
            "2026-06-17",
            278,
            0
          ],
          [
            "679",
            "2026-06-17",
            307,
            665
          ],
          [
            "679",
            "2026-06-17",
            147,
            306
          ],
          [
            "1169",
            "2026-07-06",
            42,
            0
          ],
          [
            "1169",
            "2026-07-06",
            436,
            309
          ],
          [
            "1169",
            "2026-07-06",
            638,
            0
          ],
          [
            "1169",
            "2026-07-06",
            264,
            321
          ],
          [
            "1169",
            "2026-07-06",
            241,
            327
          ],
          [
            "1169",
            "2026-07-06",
            927,
            0
          ],
          [
            "1169",
            "2026-07-06",
            94,
            0
          ],
          [
            "1169",
            "2026-07-06",
            243,
            3125
          ],
          [
            "1171",
            "2026-07-06",
            315,
            4540
          ],
          [
            "1171",
            "2026-07-06",
            101,
            0
          ],
          [
            "1171",
            "2026-07-06",
            358,
            386
          ],
          [
            "1171",
            "2026-07-06",
            593,
            3712
          ],
          [
            "1171",
            "2026-07-06",
            392,
            413
          ],
          [
            "1171",
            "2026-07-06",
            419,
            808
          ],
          [
            "1171",
            "2026-07-06",
            359,
            392
          ],
          [
            "1171",
            "2026-07-06",
            87,
            317
          ],
          [
            "1171",
            "2026-07-06",
            620,
            0
          ],
          [
            "1171",
            "2026-07-06",
            436,
            0
          ],
          [
            "1171",
            "2026-07-06",
            214,
            411
          ],
          [
            "1171",
            "2026-07-06",
            289,
            0
          ],
          [
            "1171",
            "2026-07-06",
            170,
            0
          ],
          [
            "1171",
            "2026-07-06",
            252,
            0
          ],
          [
            "1171",
            "2026-07-06",
            649,
            625
          ],
          [
            "1171",
            "2026-07-06",
            139,
            0
          ],
          [
            "1171",
            "2026-07-06",
            741,
            418
          ],
          [
            "1171",
            "2026-07-06",
            173,
            315
          ]
        ],
        "cens": [
          [
            "673",
            "2026-06-17",
            85
          ],
          [
            "675",
            "2026-06-17",
            116
          ],
          [
            "677",
            "2026-06-17",
            9
          ],
          [
            "679",
            "2026-06-17",
            1
          ],
          [
            "1169",
            "2026-07-06",
            365
          ],
          [
            "1171",
            "2026-07-06",
            105
          ]
        ]
      }
    },
    {
      "key": "game_ceiling_5050",
      "label": "ゲーム数天井・50/50",
      "ceiling": "1499G",
      "gRange": {
        "start": 0,
        "end": 610,
        "step": 10
      },
      "activeAxes": [
        "rate"
      ],
      "baseAnchors": [
        {
          "g": 0,
          "ev": 1515,
          "rtp": 113.4,
          "n": 97,
          "inv": 566,
          "playG": 430
        },
        {
          "g": 10,
          "ev": 1873,
          "rtp": 116.7,
          "n": 95,
          "inv": 561,
          "playG": 429
        },
        {
          "g": 20,
          "ev": 2195,
          "rtp": 120.1,
          "n": 95,
          "inv": 545,
          "playG": 419
        },
        {
          "g": 30,
          "ev": 2517,
          "rtp": 123.8,
          "n": 95,
          "inv": 529,
          "playG": 409
        },
        {
          "g": 40,
          "ev": 2839,
          "rtp": 127.7,
          "n": 95,
          "inv": 513,
          "playG": 399
        },
        {
          "g": 50,
          "ev": 3192,
          "rtp": 131.8,
          "n": 94,
          "inv": 502,
          "playG": 393
        },
        {
          "g": 60,
          "ev": 3514,
          "rtp": 136.1,
          "n": 94,
          "inv": 486,
          "playG": 383
        },
        {
          "g": 70,
          "ev": 3836,
          "rtp": 140.8,
          "n": 94,
          "inv": 470,
          "playG": 373
        },
        {
          "g": 80,
          "ev": 4158,
          "rtp": 145.8,
          "n": 94,
          "inv": 454,
          "playG": 363
        },
        {
          "g": 90,
          "ev": 4553,
          "rtp": 150.3,
          "n": 91,
          "inv": 453,
          "playG": 364
        },
        {
          "g": 100,
          "ev": 4979,
          "rtp": 155.7,
          "n": 89,
          "inv": 447,
          "playG": 362
        },
        {
          "g": 110,
          "ev": 5409,
          "rtp": 160.7,
          "n": 86,
          "inv": 446,
          "playG": 364
        },
        {
          "g": 120,
          "ev": 4720,
          "rtp": 153.0,
          "n": 83,
          "inv": 445,
          "playG": 360
        },
        {
          "g": 130,
          "ev": 5101,
          "rtp": 158.7,
          "n": 82,
          "inv": 435,
          "playG": 354
        },
        {
          "g": 140,
          "ev": 5490,
          "rtp": 164.8,
          "n": 81,
          "inv": 424,
          "playG": 348
        },
        {
          "g": 150,
          "ev": 5744,
          "rtp": 167.8,
          "n": 78,
          "inv": 424,
          "playG": 350
        },
        {
          "g": 160,
          "ev": 6193,
          "rtp": 172.0,
          "n": 74,
          "inv": 430,
          "playG": 357
        },
        {
          "g": 170,
          "ev": 6515,
          "rtp": 178.7,
          "n": 74,
          "inv": 414,
          "playG": 347
        },
        {
          "g": 180,
          "ev": 7143,
          "rtp": 183.6,
          "n": 69,
          "inv": 427,
          "playG": 361
        },
        {
          "g": 190,
          "ev": 6054,
          "rtp": 171.4,
          "n": 67,
          "inv": 424,
          "playG": 352
        },
        {
          "g": 200,
          "ev": 5395,
          "rtp": 165.2,
          "n": 66,
          "inv": 414,
          "playG": 341
        },
        {
          "g": 210,
          "ev": 5800,
          "rtp": 171.7,
          "n": 65,
          "inv": 404,
          "playG": 336
        },
        {
          "g": 220,
          "ev": 6086,
          "rtp": 177.2,
          "n": 64,
          "inv": 394,
          "playG": 330
        },
        {
          "g": 230,
          "ev": 6318,
          "rtp": 180.8,
          "n": 62,
          "inv": 391,
          "playG": 329
        },
        {
          "g": 240,
          "ev": 6628,
          "rtp": 185.6,
          "n": 60,
          "inv": 387,
          "playG": 328
        },
        {
          "g": 250,
          "ev": 5990,
          "rtp": 177.9,
          "n": 58,
          "inv": 384,
          "playG": 322
        },
        {
          "g": 260,
          "ev": 6417,
          "rtp": 184.0,
          "n": 56,
          "inv": 382,
          "playG": 323
        },
        {
          "g": 270,
          "ev": 6673,
          "rtp": 186.2,
          "n": 53,
          "inv": 387,
          "playG": 328
        },
        {
          "g": 280,
          "ev": 7091,
          "rtp": 190.1,
          "n": 50,
          "inv": 394,
          "playG": 336
        },
        {
          "g": 290,
          "ev": 7718,
          "rtp": 198.1,
          "n": 48,
          "inv": 393,
          "playG": 339
        },
        {
          "g": 300,
          "ev": 8207,
          "rtp": 206.4,
          "n": 47,
          "inv": 386,
          "playG": 337
        },
        {
          "g": 310,
          "ev": 8423,
          "rtp": 211.5,
          "n": 46,
          "inv": 378,
          "playG": 332
        },
        {
          "g": 320,
          "ev": 6918,
          "rtp": 193.6,
          "n": 45,
          "inv": 370,
          "playG": 317
        },
        {
          "g": 330,
          "ev": 7065,
          "rtp": 197.6,
          "n": 44,
          "inv": 362,
          "playG": 312
        },
        {
          "g": 340,
          "ev": 5790,
          "rtp": 179.8,
          "n": 42,
          "inv": 363,
          "playG": 305
        },
        {
          "g": 350,
          "ev": 6050,
          "rtp": 185.2,
          "n": 41,
          "inv": 355,
          "playG": 301
        },
        {
          "g": 360,
          "ev": 5909,
          "rtp": 178.5,
          "n": 37,
          "inv": 376,
          "playG": 316
        },
        {
          "g": 370,
          "ev": 6399,
          "rtp": 186.4,
          "n": 36,
          "inv": 370,
          "playG": 314
        },
        {
          "g": 380,
          "ev": 6540,
          "rtp": 189.6,
          "n": 35,
          "inv": 365,
          "playG": 311
        },
        {
          "g": 390,
          "ev": 3966,
          "rtp": 155.2,
          "n": 34,
          "inv": 359,
          "playG": 291
        },
        {
          "g": 400,
          "ev": 4160,
          "rtp": 158.8,
          "n": 33,
          "inv": 354,
          "playG": 288
        },
        {
          "g": 410,
          "ev": 4620,
          "rtp": 166.3,
          "n": 32,
          "inv": 349,
          "playG": 287
        },
        {
          "g": 420,
          "ev": 4727,
          "rtp": 166.6,
          "n": 30,
          "inv": 355,
          "playG": 293
        },
        {
          "g": 430,
          "ev": 5049,
          "rtp": 174.5,
          "n": 30,
          "inv": 339,
          "playG": 283
        },
        {
          "g": 440,
          "ev": 5524,
          "rtp": 179.8,
          "n": 28,
          "inv": 346,
          "playG": 291
        },
        {
          "g": 450,
          "ev": 5846,
          "rtp": 188.5,
          "n": 28,
          "inv": 330,
          "playG": 281
        },
        {
          "g": 460,
          "ev": 6020,
          "rtp": 192.4,
          "n": 27,
          "inv": 326,
          "playG": 279
        },
        {
          "g": 470,
          "ev": 6342,
          "rtp": 198.5,
          "n": 26,
          "inv": 322,
          "playG": 278
        },
        {
          "g": 480,
          "ev": 6664,
          "rtp": 208.9,
          "n": 26,
          "inv": 306,
          "playG": 268
        },
        {
          "g": 490,
          "ev": 6986,
          "rtp": 220.5,
          "n": 26,
          "inv": 290,
          "playG": 258
        },
        {
          "g": 500,
          "ev": 7308,
          "rtp": 233.5,
          "n": 26,
          "inv": 274,
          "playG": 248
        },
        {
          "g": 510,
          "ev": 7930,
          "rtp": 247.8,
          "n": 25,
          "inv": 268,
          "playG": 248
        },
        {
          "g": 520,
          "ev": 7721,
          "rtp": 246.7,
          "n": 24,
          "inv": 263,
          "playG": 243
        },
        {
          "g": 530,
          "ev": 8043,
          "rtp": 262.8,
          "n": 24,
          "inv": 247,
          "playG": 233
        },
        {
          "g": 540,
          "ev": 8768,
          "rtp": 265.1,
          "n": 21,
          "inv": 266,
          "playG": 251
        },
        {
          "g": 550,
          "ev": 9090,
          "rtp": 282.2,
          "n": 21,
          "inv": 249,
          "playG": 241
        },
        {
          "g": 560,
          "ev": 9206,
          "rtp": 277.9,
          "n": 19,
          "inv": 259,
          "playG": 248
        },
        {
          "g": 570,
          "ev": 9700,
          "rtp": 289.2,
          "n": 18,
          "inv": 256,
          "playG": 250
        },
        {
          "g": 580,
          "ev": 10871,
          "rtp": 300.4,
          "n": 16,
          "inv": 271,
          "playG": 268
        },
        {
          "g": 590,
          "ev": 11193,
          "rtp": 319.3,
          "n": 16,
          "inv": 255,
          "playG": 258
        },
        {
          "g": 600,
          "ev": 7318,
          "rtp": 243.1,
          "n": 15,
          "inv": 256,
          "playG": 235
        },
        {
          "g": 610,
          "ev": 7640,
          "rtp": 259.4,
          "n": 15,
          "inv": 240,
          "playG": 225
        }
      ],
      "zones": [],
      "totalPayout": 62222,
      "firstHitRate": 367,
      "ev": {
        "tai": 20.0,
        "kan": 20.0,
        "minSess": 15,
        "hits": [
          [
            "673",
            "2026-06-17",
            724,
            0
          ],
          [
            "673",
            "2026-06-17",
            221,
            494
          ],
          [
            "673",
            "2026-06-17",
            187,
            5041
          ],
          [
            "673",
            "2026-06-17",
            224,
            403
          ],
          [
            "673",
            "2026-06-17",
            125,
            0
          ],
          [
            "673",
            "2026-06-17",
            531,
            476
          ],
          [
            "673",
            "2026-06-17",
            321,
            733
          ],
          [
            "673",
            "2026-06-17",
            239,
            0
          ],
          [
            "673",
            "2026-06-17",
            531,
            0
          ],
          [
            "673",
            "2026-06-17",
            91,
            0
          ],
          [
            "673",
            "2026-06-17",
            157,
            713
          ],
          [
            "673",
            "2026-06-17",
            616,
            396
          ],
          [
            "673",
            "2026-06-17",
            994,
            997
          ],
          [
            "673",
            "2026-06-17",
            176,
            0
          ],
          [
            "673",
            "2026-06-17",
            572,
            307
          ],
          [
            "673",
            "2026-06-17",
            513,
            1038
          ],
          [
            "675",
            "2026-06-17",
            558,
            1122
          ],
          [
            "675",
            "2026-06-17",
            286,
            0
          ],
          [
            "675",
            "2026-06-17",
            746,
            0
          ],
          [
            "675",
            "2026-06-17",
            464,
            308
          ],
          [
            "675",
            "2026-06-17",
            385,
            5257
          ],
          [
            "675",
            "2026-06-17",
            408,
            0
          ],
          [
            "675",
            "2026-06-17",
            143,
            302
          ],
          [
            "675",
            "2026-06-17",
            613,
            3673
          ],
          [
            "675",
            "2026-06-17",
            119,
            641
          ],
          [
            "675",
            "2026-06-17",
            273,
            392
          ],
          [
            "675",
            "2026-06-17",
            370,
            638
          ],
          [
            "675",
            "2026-06-17",
            1501,
            812
          ],
          [
            "677",
            "2026-06-17",
            357,
            0
          ],
          [
            "677",
            "2026-06-17",
            179,
            0
          ],
          [
            "677",
            "2026-06-17",
            239,
            698
          ],
          [
            "677",
            "2026-06-17",
            344,
            424
          ],
          [
            "677",
            "2026-06-17",
            180,
            411
          ],
          [
            "677",
            "2026-06-17",
            578,
            0
          ],
          [
            "677",
            "2026-06-17",
            338,
            3330
          ],
          [
            "677",
            "2026-06-17",
            353,
            1332
          ],
          [
            "677",
            "2026-06-17",
            107,
            305
          ],
          [
            "677",
            "2026-06-17",
            553,
            0
          ],
          [
            "677",
            "2026-06-17",
            118,
            4404
          ],
          [
            "677",
            "2026-06-17",
            458,
            505
          ],
          [
            "677",
            "2026-06-17",
            293,
            0
          ],
          [
            "677",
            "2026-06-17",
            156,
            0
          ],
          [
            "677",
            "2026-06-17",
            195,
            3546
          ],
          [
            "677",
            "2026-06-17",
            254,
            315
          ],
          [
            "677",
            "2026-06-17",
            200,
            0
          ],
          [
            "677",
            "2026-06-17",
            153,
            0
          ],
          [
            "677",
            "2026-06-17",
            644,
            811
          ],
          [
            "679",
            "2026-06-17",
            175,
            298
          ],
          [
            "679",
            "2026-06-17",
            536,
            321
          ],
          [
            "679",
            "2026-06-17",
            85,
            0
          ],
          [
            "679",
            "2026-06-17",
            634,
            0
          ],
          [
            "679",
            "2026-06-17",
            696,
            1185
          ],
          [
            "679",
            "2026-06-17",
            335,
            750
          ],
          [
            "679",
            "2026-06-17",
            274,
            394
          ],
          [
            "679",
            "2026-06-17",
            567,
            317
          ],
          [
            "679",
            "2026-06-17",
            264,
            0
          ],
          [
            "679",
            "2026-06-17",
            266,
            838
          ],
          [
            "679",
            "2026-06-17",
            640,
            408
          ],
          [
            "679",
            "2026-06-17",
            157,
            0
          ],
          [
            "679",
            "2026-06-17",
            415,
            0
          ],
          [
            "679",
            "2026-06-17",
            140,
            497
          ],
          [
            "679",
            "2026-06-17",
            506,
            0
          ],
          [
            "679",
            "2026-06-17",
            278,
            0
          ],
          [
            "679",
            "2026-06-17",
            307,
            665
          ],
          [
            "679",
            "2026-06-17",
            147,
            306
          ],
          [
            "1169",
            "2026-07-06",
            42,
            0
          ],
          [
            "1169",
            "2026-07-06",
            436,
            309
          ],
          [
            "1169",
            "2026-07-06",
            638,
            0
          ],
          [
            "1169",
            "2026-07-06",
            264,
            321
          ],
          [
            "1169",
            "2026-07-06",
            241,
            327
          ],
          [
            "1169",
            "2026-07-06",
            927,
            0
          ],
          [
            "1169",
            "2026-07-06",
            94,
            0
          ],
          [
            "1169",
            "2026-07-06",
            243,
            3125
          ],
          [
            "1171",
            "2026-07-06",
            315,
            4540
          ],
          [
            "1171",
            "2026-07-06",
            101,
            0
          ],
          [
            "1171",
            "2026-07-06",
            358,
            386
          ],
          [
            "1171",
            "2026-07-06",
            593,
            3712
          ],
          [
            "1171",
            "2026-07-06",
            392,
            413
          ],
          [
            "1171",
            "2026-07-06",
            419,
            808
          ],
          [
            "1171",
            "2026-07-06",
            359,
            392
          ],
          [
            "1171",
            "2026-07-06",
            87,
            317
          ],
          [
            "1171",
            "2026-07-06",
            620,
            0
          ],
          [
            "1171",
            "2026-07-06",
            436,
            0
          ],
          [
            "1171",
            "2026-07-06",
            214,
            411
          ],
          [
            "1171",
            "2026-07-06",
            289,
            0
          ],
          [
            "1171",
            "2026-07-06",
            170,
            0
          ],
          [
            "1171",
            "2026-07-06",
            252,
            0
          ],
          [
            "1171",
            "2026-07-06",
            649,
            625
          ],
          [
            "1171",
            "2026-07-06",
            139,
            0
          ],
          [
            "1171",
            "2026-07-06",
            741,
            418
          ],
          [
            "1171",
            "2026-07-06",
            173,
            315
          ]
        ],
        "cens": [
          [
            "673",
            "2026-06-17",
            85
          ],
          [
            "675",
            "2026-06-17",
            116
          ],
          [
            "677",
            "2026-06-17",
            9
          ],
          [
            "679",
            "2026-06-17",
            1
          ],
          [
            "1169",
            "2026-07-06",
            365
          ],
          [
            "1171",
            "2026-07-06",
            105
          ]
        ]
      }
    }
  ],
  "axes": [
    {
      "key": "rate",
      "label": "レート",
      "type": "select",
      "pivotable": false,
      "default": "tab",
      "options": [
        {
          "value": "tab",
          "label": "レートは上のタブで切替（46/52・50/50）"
        }
      ]
    }
  ],
  "modifiers": {
    "rate": {
      "tab": 0
    }
  },
  "creditValue": {
    "tab": 19.23076923076923
  },
  "economics": {
    "medalsPerGame": 1.61,
    "gamesPerHour": 800
  }
}